strahlenexposition_uba/__init__.py
strahlenexposition_uba/__main__.py
strahlenexposition_uba/assets/Logo_BfS_DE.png
strahlenexposition_uba/assets/excel_to_sqlite.svg
strahlenexposition_uba/assets/ki-lab-logo.png
strahlenexposition_uba/assets/style.css
strahlenexposition_uba/constants.py
strahlenexposition_uba/dashboard.py
strahlenexposition_uba/data_science.py
strahlenexposition_uba/database.py
strahlenexposition_uba/excel_to_db.py
strahlenexposition_uba/formatter.py
strahlenexposition_uba/heatmaps.py
strahlenexposition_uba/logger_config.py
strahlenexposition_uba/pipeline.py
strahlenexposition_uba/preprocess.py
strahlenexposition_uba/report.py
strahlenexposition_uba/sql/create_view.sql
strahlenexposition_uba/sql/schema.sql
strahlenexposition_uba/templates/report_template.html
strahlenexposition_uba/tmp_insert_data.py
strahlenexposition_uba/visualisation.py
strahlenexposition_uba-1.0.0.dist-info/LICENSE
strahlenexposition_uba-1.0.0.dist-info/METADATA
strahlenexposition_uba-1.0.0.dist-info/WHEEL
strahlenexposition_uba-1.0.0.dist-info/RECORD
