Metadata-Version: 2.3
Name: strahlenexposition_uba
Version: 1.0.0
Summary: Package for importing, processing and visualising radition exposure data
License: MIT
Keywords: radiation,data processing,visualization
Author: Viola Rädle
Author-email: viola.raedle@uba.de
Requires-Python: >=3.10
Classifier: Programming Language :: Python :: 3
Classifier: Operating System :: OS Independent
Requires-Dist: adjusttext (>=1.3.0,<2.0.0)
Requires-Dist: dash (>=2.18.2,<3.0.0)
Requires-Dist: dash-ag-grid (>=31.3.0,<32.0.0)
Requires-Dist: dash-bootstrap-components (>=1.7.1,<2.0.0)
Requires-Dist: fastexcel (>=0.12.1,<0.13.0)
Requires-Dist: kaleido (==0.1.0.post1) ; sys_platform == "win32"
Requires-Dist: kaleido (==0.2.1) ; sys_platform != "win32"
Requires-Dist: matplotlib (>=3.10.1,<4.0.0)
Requires-Dist: msgpack (>=1.1.0,<2.0.0)
Requires-Dist: numpy (>=2.2.2,<3.0.0)
Requires-Dist: pandas (>=2.2.3,<3.0.0)
Requires-Dist: plotly (>=6.0.0,<7.0.0)
Requires-Dist: polars (>=1.21.0,<2.0.0)
Requires-Dist: scikit-learn (>=1.6.1,<2.0.0)
Requires-Dist: weasyprint (>=64.1,<65.0)
Requires-Dist: xlsxwriter (>=3.2.3,<4.0.0)
